tomoviz/__init__.py
tomoviz/bibtex.py
tomoviz/icon.png
tomoviz/icon_square.png
tomoviz/loading.gif
tomoviz/protocols.conf
tomoviz/utils.py
tomoviz/protocols/__init__.py
tomoviz/protocols/protocol_mesh_normal.py
tomoviz/protocols/protocol_particle_pick_consensus.py
tomoviz/protocols/protocol_particle_pick_remove_duplicates.py
tomoviz/tests/__init__.py
tomoviz/tests/test_tomo3D_base.py
tomoviz/viewers/__init__.py
tomoviz/viewers/viewer_mrc.py
tomoviz/viewers/viewer_triangulations.py
tomoviz/viewers/viewer_vtk.py
tomoviz/viewers/viewers_data.py
tomoviz/viewers/views_tkinter_tree.py
scipion_em_tomoviz-3.2.1.dist-info/LICENSE
scipion_em_tomoviz-3.2.1.dist-info/METADATA
scipion_em_tomoviz-3.2.1.dist-info/WHEEL
scipion_em_tomoviz-3.2.1.dist-info/entry_points.txt
scipion_em_tomoviz-3.2.1.dist-info/top_level.txt
scipion_em_tomoviz-3.2.1.dist-info/RECORD
