Metadata-Version: 2.1
Name: scipion-em-tomoviz
Version: 3.2.1
Summary: Tools for 3D visualization and manipulation of tomography data
Home-page: https://github.com/scipion-em/scipion-em-tomoviz
Author: you
Author-email: you@yourinstitution.email
License: UNKNOWN
Keywords: scipion tomography imageprocessing scipion-3.0
Platform: UNKNOWN
Classifier: Development Status :: 4 - Beta
Classifier: License :: OSI Approved :: GNU General Public License v3 (GPLv3)
Classifier: Programming Language :: Python :: 3
Requires-Dist: scipion-pyworkflow
Requires-Dist: scipion-em>=3.0.8
Requires-Dist: scipion-em-tomo
Requires-Dist: pyvista==0.38.5
Requires-Dist: pyvistaqt==0.10.0
Requires-Dist: pymeshfix==0.16.0
Requires-Dist: scikit-image>=0.19
Requires-Dist: PyQt5
